visier/__init__.py
visier/sdk/__init__.py
visier/sdk/api/__init__.py
visier/sdk/api/analytic_model/__init__.py
visier/sdk/api/analytic_model/api_client.py
visier/sdk/api/analytic_model/api_response.py
visier/sdk/api/analytic_model/configuration.py
visier/sdk/api/analytic_model/exceptions.py
visier/sdk/api/analytic_model/py.typed
visier/sdk/api/analytic_model/rest.py
visier/sdk/api/analytic_model/api/__init__.py
visier/sdk/api/analytic_model/api/data_model_api.py
visier/sdk/api/analytic_model/api/object_configuration_api.py
visier/sdk/api/analytic_model/models/__init__.py
visier/sdk/api/analytic_model/models/aggregation_type_option_dto.py
visier/sdk/api/analytic_model/models/aggregation_type_parameter_dto.py
visier/sdk/api/analytic_model/models/analytic_object_dto.py
visier/sdk/api/analytic_model/models/analytic_object_filter_dto.py
visier/sdk/api/analytic_model/models/analytic_objects_dto.py
visier/sdk/api/analytic_model/models/calculation_concept_configuration_dto.py
visier/sdk/api/analytic_model/models/calculation_concept_configuration_map_dto.py
visier/sdk/api/analytic_model/models/calculation_concept_dto.py
visier/sdk/api/analytic_model/models/calculation_concept_list_dto.py
visier/sdk/api/analytic_model/models/concept_configuration_result_dto.py
visier/sdk/api/analytic_model/models/currencies_dto.py
visier/sdk/api/analytic_model/models/currency_dto.py
visier/sdk/api/analytic_model/models/currency_rate_dto.py
visier/sdk/api/analytic_model/models/currency_rates_dto.py
visier/sdk/api/analytic_model/models/dimension_dto.py
visier/sdk/api/analytic_model/models/dimension_filter_dto.py
visier/sdk/api/analytic_model/models/dimension_mapping_validation_dto.py
visier/sdk/api/analytic_model/models/dimension_mapping_validation_execution_dto.py
visier/sdk/api/analytic_model/models/dimension_member_dto.py
visier/sdk/api/analytic_model/models/dimension_member_reference_dto.py
visier/sdk/api/analytic_model/models/dimension_reference_dto.py
visier.sdk.api.analytic_model-22222222.99201.1456.dist-info/METADATA
visier.sdk.api.analytic_model-22222222.99201.1456.dist-info/WHEEL
visier.sdk.api.analytic_model-22222222.99201.1456.dist-info/top_level.txt
visier.sdk.api.analytic_model-22222222.99201.1456.dist-info/RECORD
