Metadata-Version: 2.1
Name: visier.sdk.api.analytic-model
Version: 22222222.99201.1456
Summary: Visier Analytic Model APIs
Home-page: 
Author: OpenAPI Generator community
Author-email: team@openapitools.org
License: Apache License, Version 2.0
Keywords: OpenAPI,OpenAPI-Generator,Visier Analytic Model APIs
Requires-Dist: urllib3 <2.1.0,>=1.25.3
Requires-Dist: python-dateutil
Requires-Dist: pydantic >=2
Requires-Dist: typing-extensions >=4.7.1
